varify_client
