Metadata-Version: 1.1
Name: varify-client
Version: 0.0.3
Summary: an HTTP client and supporting utilities for the Varify API
Home-page: https://github.com/awenocur/varify_client
Author: Adam Wenocour
Author-email: wenocur@email.chop.edu
License: UNKNOWN
Download-URL: https://github.com/awenocur/varify_client.git
Platform: UNKNOWN
